{
  "project_info": {
    "project_number": "611972257323",
    "firebase_url": "https://covid19es-41ab2.firebaseio.com",
    "project_id": "covid19es-41ab2",
    "storage_bucket": "covid19es-41ab2.appspot.com"
  },
  "client": [
    {
      "client_info": {
        "mobilesdk_app_id": "1:611972257323:android:7001cb7bcd97759e8e3c6e",
        "android_client_info": {
          "package_name": "es.covid19es.app"
        }
      },
      "oauth_client": [
        {
          "client_id": "611972257323-3jpp8ugu7qsctusk7p8ftvttbpnop556.apps.googleusercontent.com",
          "client_type": 1,
          "android_info": {
            "package_name": "es.covid19es.app",
            "certificate_hash": "8987c701e59d51d4d3481112d397789d5e7204ed"
          }
        },
        {
          "client_id": "611972257323-8bv2dv5bkovcji3slpt3bro4eifb0n4t.apps.googleusercontent.com",
          "client_type": 3
        }
      ],
      "api_key": [
        {
          "current_key": "AIzaSyAl-s7gb412pPuawudOIlWw7Uu2saoH1vc"
        }
      ],
      "services": {
        "appinvite_service": {
          "other_platform_oauth_client": [
            {
              "client_id": "611972257323-8bv2dv5bkovcji3slpt3bro4eifb0n4t.apps.googleusercontent.com",
              "client_type": 3
            }
          ]
        }
      }
    },
    {
      "client_info": {
        "mobilesdk_app_id": "1:611972257323:android:27d09222b6beceac8e3c6e",
        "android_client_info": {
          "package_name": "es.covid19es.app.dev"
        }
      },
      "oauth_client": [
        {
          "client_id": "611972257323-ippugoa9jdhllhldvg9bjhsbk9if6ug3.apps.googleusercontent.com",
          "client_type": 1,
          "android_info": {
            "package_name": "es.covid19es.app.dev",
            "certificate_hash": "8987c701e59d51d4d3481112d397789d5e7204ed"
          }
        },
        {
          "client_id": "611972257323-8bv2dv5bkovcji3slpt3bro4eifb0n4t.apps.googleusercontent.com",
          "client_type": 3
        }
      ],
      "api_key": [
        {
          "current_key": "AIzaSyAl-s7gb412pPuawudOIlWw7Uu2saoH1vc"
        }
      ],
      "services": {
        "appinvite_service": {
          "other_platform_oauth_client": [
            {
              "client_id": "611972257323-8bv2dv5bkovcji3slpt3bro4eifb0n4t.apps.googleusercontent.com",
              "client_type": 3
            }
          ]
        }
      }
    }
  ],
  "configuration_version": "1"
}